weni/__init__.py
weni/eda/__init__.py
weni/eda/backends/__init__.py
weni/eda/backends/pyamqp/__init__.py
weni/eda/backends/pyamqp/tests/__init__.py
weni/eda/backends/pyamqp/tests/test_connection.py
weni/eda/backends/pyamqp_backend.py
weni/eda/connection.py
weni/eda/connection_params/__init__.py
weni/eda/connection_params/connection_params.py
weni/eda/connection_params/factory.py
weni/eda/django/__init__.py
weni/eda/django/connection_params.py
weni/eda/django/consumers/__init__.py
weni/eda/django/consumers/consumer.py
weni/eda/django/consumers/signals.py
weni/eda/django/eda_app/__init__.py
weni/eda/django/eda_app/apps.py
weni/eda/django/eda_app/management/__init__.py
weni/eda/django/eda_app/management/commands/__init__.py
weni/eda/django/eda_app/management/commands/edaconsume.py
weni/eda/eda_publisher.py
weni/eda/parsers/__init__.py
weni/eda/parsers/exceptions.py
weni/eda/parsers/json_parser.py
weni/eda/parsers/parser.py
weni/eda/parsers/tests/test_json_parser.py
weni_eda-0.1.1.dist-info/METADATA
weni_eda-0.1.1.dist-info/WHEEL
weni_eda-0.1.1.dist-info/RECORD
