Metadata-Version: 2.1
Name: weni-eda
Version: 0.1.1
Summary: 
Author: Weni
Requires-Python: >=3.10,<4.0
Classifier: Programming Language :: Python :: 3
Classifier: Programming Language :: Python :: 3.10
Classifier: Programming Language :: Python :: 3.11
Classifier: Programming Language :: Python :: 3.12
Requires-Dist: amqp (>=5.2.0,<6.0.0)
